ftp_brute_force/VERSION
ftp_brute_force/__init__.py
ftp_brute_force/ftp_brute_force.py
ftp_brute_force/load_dict.cpython-313-x86_64-linux-gnu.so
ftp_brute_force/load_dict.pyi
ftp_brute-0.1.9.dist-info/LICENSE
ftp_brute-0.1.9.dist-info/METADATA
ftp_brute-0.1.9.dist-info/WHEEL
ftp_brute-0.1.9.dist-info/entry_points.txt
ftp_brute-0.1.9.dist-info/top_level.txt
ftp_brute-0.1.9.dist-info/RECORD
