Metadata-Version: 2.2
Name: ftp_brute
Version: 0.1.9
Summary: A FTP brute force tool
Home-page: https://github.com/jacksonjapy/ftp_brute_force
Author: Jackson Ja
Author-email: jackson2937703346@163.com
Classifier: Programming Language :: Python :: 3
Classifier: License :: OSI Approved :: MIT License
Classifier: Operating System :: OS Independent
Requires-Python: >=3.10
License-File: LICENSE
Dynamic: author
Dynamic: author-email
Dynamic: classifier
Dynamic: description
Dynamic: description-content-type
Dynamic: home-page
Dynamic: requires-python
Dynamic: summary
